{
    "extraction": {
        "siret": "98976238423645",
        "siren": "989762384",
        "numero_document": "FA-2027-5582",
        "date": null,
        "date_expiration": null,
        "fournisseur": null,
        "iban": null,
        "montant_ttc": "817.05",
        "montant_ht": "750.54",
        "tva_montant": "15.97",
        "tva_taux": null,
        "document_id": "FA-2027-5582",
        "type_document": "facture"
    },
    "texte_brut": "\n        FACTURE N° FA-2027-5582\n        Date de facturation : 2027-04-09\n        Echéance : 2027-10-23\n        \n        EMETTEUR :\n        Bazin Élisabeth\n        SIRET : 98976238423645\n        TVA : FR21 989762384\n        Adresse : 77, boulevard Manon Gilles, 34127 Cohen\n        \n        MONTANTS :\n        Total HT : 750.54 €\n        TVA : 15.97 €\n        Total TTC : 817.05 €\n        ",
    "meta": {
        "fichier_source": "FA-2027-5582.json",
        "document_id": "FA-2027-5582",
        "type_document": "facture",
        "date_traitement": "2026-03-17T14:25:06.213631",
        "statut": "succes"
    },
    "verification_metier": {
        "sirene": {
            "incoherences": [
                "SIRET invalide ou inconnu : SIREN introuvable dans la base"
            ],
            "verification_sirene": {
                "valide": false,
                "siren": "989762384",
                "erreur": "SIREN introuvable dans la base"
            }
        },
        "expiration": {
            "statut": "inconnu",
            "details": "Aucune date (d'émission ou d'expiration) détectée, impossible de vérifier.",
            "expire": null
        },
        "statut_final": "valide",
        "alertes": [],
        "traite_le": "2026-03-17T14:25:06.944743"
    }
}